{"nodes": [{"id": "model_utils", "label": "model_utils.py", "file_type": "code", "source_file": "mineru\\mineru\\utils\\model_utils.py", "source_location": "L1"}, {"id": "model_utils_get_bbox", "label": "_get_bbox()", "file_type": "code", "source_file": "mineru\\mineru\\utils\\model_utils.py", "source_location": "L38"}, {"id": "model_utils_get_int_bbox", "label": "_get_int_bbox()", "file_type": "code", "source_file": "mineru\\mineru\\utils\\model_utils.py", "source_location": "L45"}, {"id": "model_utils_crop_img", "label": "crop_img()", "file_type": "code", "source_file": "mineru\\mineru\\utils\\model_utils.py", "source_location": "L50"}, {"id": "model_utils_get_coords_and_area", "label": "get_coords_and_area()", "file_type": "code", "source_file": "mineru\\mineru\\utils\\model_utils.py", "source_location": "L81"}, {"id": "model_utils_calculate_intersection", "label": "calculate_intersection()", "file_type": "code", "source_file": "mineru\\mineru\\utils\\model_utils.py", "source_location": "L88"}, {"id": "model_utils_is_inside", "label": "is_inside()", "file_type": "code", "source_file": "mineru\\mineru\\utils\\model_utils.py", "source_location": "L102"}, {"id": "model_utils_remove_nested_ocr_text_blocks", "label": "remove_nested_ocr_text_blocks()", "file_type": "code", "source_file": "mineru\\mineru\\utils\\model_utils.py", "source_location": "L116"}, {"id": "model_utils_get_res_list_from_layout_res", "label": "get_res_list_from_layout_res()", "file_type": "code", "source_file": "mineru\\mineru\\utils\\model_utils.py", "source_location": "L148"}, {"id": "model_utils_clean_memory", "label": "clean_memory()", "file_type": "code", "source_file": "mineru\\mineru\\utils\\model_utils.py", "source_location": "L183"}, {"id": "model_utils_clean_vram", "label": "clean_vram()", "file_type": "code", "source_file": "mineru\\mineru\\utils\\model_utils.py", "source_location": "L208"}, {"id": "model_utils_get_vram", "label": "get_vram()", "file_type": "code", "source_file": "mineru\\mineru\\utils\\model_utils.py", "source_location": "L217"}, {"id": "model_utils_rationale_82", "label": "Extract coordinates and area from a table.", "file_type": "rationale", "source_file": "mineru\\mineru\\utils\\model_utils.py", "source_location": "L82"}, {"id": "model_utils_rationale_89", "label": "Calculate intersection coordinates between two boxes.", "file_type": "rationale", "source_file": "mineru\\mineru\\utils\\model_utils.py", "source_location": "L89"}, {"id": "model_utils_rationale_103", "label": "Check if small_box is inside big_box by at least overlap_threshold.", "file_type": "rationale", "source_file": "mineru\\mineru\\utils\\model_utils.py", "source_location": "L103"}, {"id": "model_utils_rationale_122", "label": "Remove OCR candidate text blocks that are contained by any larger layout block.", "file_type": "rationale", "source_file": "mineru\\mineru\\utils\\model_utils.py", "source_location": "L122"}, {"id": "model_utils_rationale_149", "label": "Extract OCR, table and other regions from layout results.", "file_type": "rationale", "source_file": "mineru\\mineru\\utils\\model_utils.py", "source_location": "L149"}], "edges": [{"source": "model_utils", "target": "math", "relation": "imports", "confidence": "EXTRACTED", "source_file": "mineru\\mineru\\utils\\model_utils.py", "source_location": "L2", "weight": 1.0}, {"source": "model_utils", "target": "os", "relation": "imports", "confidence": "EXTRACTED", "source_file": "mineru\\mineru\\utils\\model_utils.py", "source_location": "L3", "weight": 1.0}, {"source": "model_utils", "target": "time", "relation": "imports", "confidence": "EXTRACTED", "source_file": "mineru\\mineru\\utils\\model_utils.py", "source_location": "L4", "weight": 1.0}, {"source": "model_utils", "target": "gc", "relation": "imports", "confidence": "EXTRACTED", "source_file": "mineru\\mineru\\utils\\model_utils.py", "source_location": "L5", "weight": 1.0}, {"source": "model_utils", "target": "pil", "relation": "imports_from", "confidence": "EXTRACTED", "source_file": "mineru\\mineru\\utils\\model_utils.py", "source_location": "L6", "weight": 1.0}, {"source": "model_utils", "target": "loguru", "relation": "imports_from", "confidence": "EXTRACTED", "source_file": "mineru\\mineru\\utils\\model_utils.py", "source_location": "L7", "weight": 1.0}, {"source": "model_utils", "target": "numpy", "relation": "imports", "confidence": "EXTRACTED", "source_file": "mineru\\mineru\\utils\\model_utils.py", "source_location": "L8", "weight": 1.0}, {"source": "model_utils", "target": "torch", "relation": "imports", "confidence": "EXTRACTED", "source_file": "mineru\\mineru\\utils\\model_utils.py", "source_location": "L11", "weight": 1.0}, {"source": "model_utils", "target": "torch_npu", "relation": "imports", "confidence": "EXTRACTED", "source_file": "mineru\\mineru\\utils\\model_utils.py", "source_location": "L12", "weight": 1.0}, {"source": "model_utils", "target": "model_utils_get_bbox", "relation": "contains", "confidence": "EXTRACTED", "source_file": "mineru\\mineru\\utils\\model_utils.py", "source_location": "L38", "weight": 1.0}, {"source": "model_utils", "target": "model_utils_get_int_bbox", "relation": "contains", "confidence": "EXTRACTED", "source_file": "mineru\\mineru\\utils\\model_utils.py", "source_location": "L45", "weight": 1.0}, {"source": "model_utils", "target": "model_utils_crop_img", "relation": "contains", "confidence": "EXTRACTED", "source_file": "mineru\\mineru\\utils\\model_utils.py", "source_location": "L50", "weight": 1.0}, {"source": "model_utils", "target": "model_utils_get_coords_and_area", "relation": "contains", "confidence": "EXTRACTED", "source_file": "mineru\\mineru\\utils\\model_utils.py", "source_location": "L81", "weight": 1.0}, {"source": "model_utils", "target": "model_utils_calculate_intersection", "relation": "contains", "confidence": "EXTRACTED", "source_file": "mineru\\mineru\\utils\\model_utils.py", "source_location": "L88", "weight": 1.0}, {"source": "model_utils", "target": "model_utils_is_inside", "relation": "contains", "confidence": "EXTRACTED", "source_file": "mineru\\mineru\\utils\\model_utils.py", "source_location": "L102", "weight": 1.0}, {"source": "model_utils", "target": "model_utils_remove_nested_ocr_text_blocks", "relation": "contains", "confidence": "EXTRACTED", "source_file": "mineru\\mineru\\utils\\model_utils.py", "source_location": "L116", "weight": 1.0}, {"source": "model_utils", "target": "model_utils_get_res_list_from_layout_res", "relation": "contains", "confidence": "EXTRACTED", "source_file": "mineru\\mineru\\utils\\model_utils.py", "source_location": "L148", "weight": 1.0}, {"source": "model_utils", "target": "model_utils_clean_memory", "relation": "contains", "confidence": "EXTRACTED", "source_file": "mineru\\mineru\\utils\\model_utils.py", "source_location": "L183", "weight": 1.0}, {"source": "model_utils", "target": "model_utils_clean_vram", "relation": "contains", "confidence": "EXTRACTED", "source_file": "mineru\\mineru\\utils\\model_utils.py", "source_location": "L208", "weight": 1.0}, {"source": "model_utils", "target": "model_utils_get_vram", "relation": "contains", "confidence": "EXTRACTED", "source_file": "mineru\\mineru\\utils\\model_utils.py", "source_location": "L217", "weight": 1.0}, {"source": "model_utils_get_int_bbox", "target": "model_utils_get_bbox", "relation": "calls", "confidence": "EXTRACTED", "source_file": "mineru\\mineru\\utils\\model_utils.py", "source_location": "L46", "weight": 1.0}, {"source": "model_utils_crop_img", "target": "model_utils_get_int_bbox", "relation": "calls", "confidence": "EXTRACTED", "source_file": "mineru\\mineru\\utils\\model_utils.py", "source_location": "L51", "weight": 1.0}, {"source": "model_utils_get_coords_and_area", "target": "model_utils_get_bbox", "relation": "calls", "confidence": "EXTRACTED", "source_file": "mineru\\mineru\\utils\\model_utils.py", "source_location": "L83", "weight": 1.0}, {"source": "model_utils_is_inside", "target": "model_utils_calculate_intersection", "relation": "calls", "confidence": "EXTRACTED", "source_file": "mineru\\mineru\\utils\\model_utils.py", "source_location": "L104", "weight": 1.0}, {"source": "model_utils_remove_nested_ocr_text_blocks", "target": "model_utils_get_coords_and_area", "relation": "calls", "confidence": "EXTRACTED", "source_file": "mineru\\mineru\\utils\\model_utils.py", "source_location": "L126", "weight": 1.0}, {"source": "model_utils_remove_nested_ocr_text_blocks", "target": "model_utils_is_inside", "relation": "calls", "confidence": "EXTRACTED", "source_file": "mineru\\mineru\\utils\\model_utils.py", "source_location": "L137", "weight": 1.0}, {"source": "model_utils_get_res_list_from_layout_res", "target": "model_utils_get_bbox", "relation": "calls", "confidence": "EXTRACTED", "source_file": "mineru\\mineru\\utils\\model_utils.py", "source_location": "L160", "weight": 1.0}, {"source": "model_utils_get_res_list_from_layout_res", "target": "model_utils_remove_nested_ocr_text_blocks", "relation": "calls", "confidence": "EXTRACTED", "source_file": "mineru\\mineru\\utils\\model_utils.py", "source_location": "L171", "weight": 1.0}, {"source": "model_utils_clean_vram", "target": "model_utils_get_vram", "relation": "calls", "confidence": "EXTRACTED", "source_file": "mineru\\mineru\\utils\\model_utils.py", "source_location": "L209", "weight": 1.0}, {"source": "model_utils_clean_vram", "target": "model_utils_clean_memory", "relation": "calls", "confidence": "EXTRACTED", "source_file": "mineru\\mineru\\utils\\model_utils.py", "source_location": "L212", "weight": 1.0}, {"source": "model_utils_rationale_82", "target": "model_utils_get_coords_and_area", "relation": "rationale_for", "confidence": "EXTRACTED", "source_file": "mineru\\mineru\\utils\\model_utils.py", "source_location": "L82", "weight": 1.0}, {"source": "model_utils_rationale_89", "target": "model_utils_calculate_intersection", "relation": "rationale_for", "confidence": "EXTRACTED", "source_file": "mineru\\mineru\\utils\\model_utils.py", "source_location": "L89", "weight": 1.0}, {"source": "model_utils_rationale_103", "target": "model_utils_is_inside", "relation": "rationale_for", "confidence": "EXTRACTED", "source_file": "mineru\\mineru\\utils\\model_utils.py", "source_location": "L103", "weight": 1.0}, {"source": "model_utils_rationale_122", "target": "model_utils_remove_nested_ocr_text_blocks", "relation": "rationale_for", "confidence": "EXTRACTED", "source_file": "mineru\\mineru\\utils\\model_utils.py", "source_location": "L122", "weight": 1.0}, {"source": "model_utils_rationale_149", "target": "model_utils_get_res_list_from_layout_res", "relation": "rationale_for", "confidence": "EXTRACTED", "source_file": "mineru\\mineru\\utils\\model_utils.py", "source_location": "L149", "weight": 1.0}]}