{"nodes": [{"id": "pytorchocr_utility", "label": "pytorchocr_utility.py", "file_type": "code", "source_file": "mineru\\mineru\\model\\utils\\tools\\infer\\pytorchocr_utility.py", "source_location": "L1"}, {"id": "pytorchocr_utility_init_args", "label": "init_args()", "file_type": "code", "source_file": "mineru\\mineru\\model\\utils\\tools\\infer\\pytorchocr_utility.py", "source_location": "L14"}, {"id": "pytorchocr_utility_parse_args", "label": "parse_args()", "file_type": "code", "source_file": "mineru\\mineru\\model\\utils\\tools\\infer\\pytorchocr_utility.py", "source_location": "L145"}, {"id": "pytorchocr_utility_get_default_config", "label": "get_default_config()", "file_type": "code", "source_file": "mineru\\mineru\\model\\utils\\tools\\infer\\pytorchocr_utility.py", "source_location": "L149"}, {"id": "pytorchocr_utility_read_network_config_from_yaml", "label": "read_network_config_from_yaml()", "file_type": "code", "source_file": "mineru\\mineru\\model\\utils\\tools\\infer\\pytorchocr_utility.py", "source_location": "L153"}, {"id": "pytorchocr_utility_analysisconfig", "label": "AnalysisConfig()", "file_type": "code", "source_file": "mineru\\mineru\\model\\utils\\tools\\infer\\pytorchocr_utility.py", "source_location": "L169"}, {"id": "pytorchocr_utility_resize_img", "label": "resize_img()", "file_type": "code", "source_file": "mineru\\mineru\\model\\utils\\tools\\infer\\pytorchocr_utility.py", "source_location": "L177"}, {"id": "pytorchocr_utility_str_count", "label": "str_count()", "file_type": "code", "source_file": "mineru\\mineru\\model\\utils\\tools\\infer\\pytorchocr_utility.py", "source_location": "L189"}, {"id": "pytorchocr_utility_base64_to_cv2", "label": "base64_to_cv2()", "file_type": "code", "source_file": "mineru\\mineru\\model\\utils\\tools\\infer\\pytorchocr_utility.py", "source_location": "L213"}, {"id": "pytorchocr_utility_get_arch_config", "label": "get_arch_config()", "file_type": "code", "source_file": "mineru\\mineru\\model\\utils\\tools\\infer\\pytorchocr_utility.py", "source_location": "L221"}, {"id": "pytorchocr_utility_rationale_178", "label": "resize img and limit the longest side of the image to input_size", "file_type": "rationale", "source_file": "mineru\\mineru\\model\\utils\\tools\\infer\\pytorchocr_utility.py", "source_location": "L178"}, {"id": "pytorchocr_utility_rationale_190", "label": "Count the number of Chinese characters,\r     a single English character and a si", "file_type": "rationale", "source_file": "mineru\\mineru\\model\\utils\\tools\\infer\\pytorchocr_utility.py", "source_location": "L190"}], "edges": [{"source": "pytorchocr_utility", "target": "os", "relation": "imports", "confidence": "EXTRACTED", "source_file": "mineru\\mineru\\model\\utils\\tools\\infer\\pytorchocr_utility.py", "source_location": "L2", "weight": 1.0}, {"source": "pytorchocr_utility", "target": "math", "relation": "imports", "confidence": "EXTRACTED", "source_file": "mineru\\mineru\\model\\utils\\tools\\infer\\pytorchocr_utility.py", "source_location": "L3", "weight": 1.0}, {"source": "pytorchocr_utility", "target": "pathlib", "relation": "imports_from", "confidence": "EXTRACTED", "source_file": "mineru\\mineru\\model\\utils\\tools\\infer\\pytorchocr_utility.py", "source_location": "L4", "weight": 1.0}, {"source": "pytorchocr_utility", "target": "numpy", "relation": "imports", "confidence": "EXTRACTED", "source_file": "mineru\\mineru\\model\\utils\\tools\\infer\\pytorchocr_utility.py", "source_location": "L5", "weight": 1.0}, {"source": "pytorchocr_utility", "target": "cv2", "relation": "imports", "confidence": "EXTRACTED", "source_file": "mineru\\mineru\\model\\utils\\tools\\infer\\pytorchocr_utility.py", "source_location": "L6", "weight": 1.0}, {"source": "pytorchocr_utility", "target": "argparse", "relation": "imports", "confidence": "EXTRACTED", "source_file": "mineru\\mineru\\model\\utils\\tools\\infer\\pytorchocr_utility.py", "source_location": "L7", "weight": 1.0}, {"source": "pytorchocr_utility", "target": "pytorchocr_utility_init_args", "relation": "contains", "confidence": "EXTRACTED", "source_file": "mineru\\mineru\\model\\utils\\tools\\infer\\pytorchocr_utility.py", "source_location": "L14", "weight": 1.0}, {"source": "pytorchocr_utility", "target": "pytorchocr_utility_parse_args", "relation": "contains", "confidence": "EXTRACTED", "source_file": "mineru\\mineru\\model\\utils\\tools\\infer\\pytorchocr_utility.py", "source_location": "L145", "weight": 1.0}, {"source": "pytorchocr_utility", "target": "pytorchocr_utility_get_default_config", "relation": "contains", "confidence": "EXTRACTED", "source_file": "mineru\\mineru\\model\\utils\\tools\\infer\\pytorchocr_utility.py", "source_location": "L149", "weight": 1.0}, {"source": "pytorchocr_utility", "target": "pytorchocr_utility_read_network_config_from_yaml", "relation": "contains", "confidence": "EXTRACTED", "source_file": "mineru\\mineru\\model\\utils\\tools\\infer\\pytorchocr_utility.py", "source_location": "L153", "weight": 1.0}, {"source": "pytorchocr_utility", "target": "pytorchocr_utility_analysisconfig", "relation": "contains", "confidence": "EXTRACTED", "source_file": "mineru\\mineru\\model\\utils\\tools\\infer\\pytorchocr_utility.py", "source_location": "L169", "weight": 1.0}, {"source": "pytorchocr_utility", "target": "pytorchocr_utility_resize_img", "relation": "contains", "confidence": "EXTRACTED", "source_file": "mineru\\mineru\\model\\utils\\tools\\infer\\pytorchocr_utility.py", "source_location": "L177", "weight": 1.0}, {"source": "pytorchocr_utility", "target": "pytorchocr_utility_str_count", "relation": "contains", "confidence": "EXTRACTED", "source_file": "mineru\\mineru\\model\\utils\\tools\\infer\\pytorchocr_utility.py", "source_location": "L189", "weight": 1.0}, {"source": "pytorchocr_utility", "target": "pytorchocr_utility_base64_to_cv2", "relation": "contains", "confidence": "EXTRACTED", "source_file": "mineru\\mineru\\model\\utils\\tools\\infer\\pytorchocr_utility.py", "source_location": "L213", "weight": 1.0}, {"source": "pytorchocr_utility", "target": "pytorchocr_utility_get_arch_config", "relation": "contains", "confidence": "EXTRACTED", "source_file": "mineru\\mineru\\model\\utils\\tools\\infer\\pytorchocr_utility.py", "source_location": "L221", "weight": 1.0}, {"source": "pytorchocr_utility_parse_args", "target": "pytorchocr_utility_init_args", "relation": "calls", "confidence": "EXTRACTED", "source_file": "mineru\\mineru\\model\\utils\\tools\\infer\\pytorchocr_utility.py", "source_location": "L146", "weight": 1.0}, {"source": "pytorchocr_utility_analysisconfig", "target": "pytorchocr_utility_read_network_config_from_yaml", "relation": "calls", "confidence": "EXTRACTED", "source_file": "mineru\\mineru\\model\\utils\\tools\\infer\\pytorchocr_utility.py", "source_location": "L174", "weight": 1.0}, {"source": "pytorchocr_utility_rationale_178", "target": "pytorchocr_utility_resize_img", "relation": "rationale_for", "confidence": "EXTRACTED", "source_file": "mineru\\mineru\\model\\utils\\tools\\infer\\pytorchocr_utility.py", "source_location": "L178", "weight": 1.0}, {"source": "pytorchocr_utility_rationale_190", "target": "pytorchocr_utility_str_count", "relation": "rationale_for", "confidence": "EXTRACTED", "source_file": "mineru\\mineru\\model\\utils\\tools\\infer\\pytorchocr_utility.py", "source_location": "L190", "weight": 1.0}]}